bd103/__init__.py
bd103/data/__init__.py
bd103/decorators.py
bd103/ext/__init__.py
bd103/ext/trio.py
bd103/richtext.py
bd103/shared/__init__.py
bd103-2.0.0.dist-info/entry_points.txt
bd103-2.0.0.dist-info/LICENSE
bd103-2.0.0.dist-info/WHEEL
bd103-2.0.0.dist-info/METADATA
bd103-2.0.0.dist-info/RECORD
