Metadata-Version: 2.1
Name: bd103
Version: 2.0.0
Summary: BD103's Python Package
Home-page: https://bd103.github.io
License: Apache-2.0
Author: BD103
Author-email: dont@stalk.me
Requires-Python: >=3.9,<4.0
Classifier: License :: OSI Approved :: Apache Software License
Classifier: Programming Language :: Python :: 3
Classifier: Programming Language :: Python :: 3.10
Classifier: Programming Language :: Python :: 3.9
Provides-Extra: docs
Provides-Extra: ext
Requires-Dist: sphinx (>=4.3.1,<5.0.0); extra == "docs"
Requires-Dist: trio (>=0.19.0,<0.20.0); extra == "ext"
Project-URL: Repository, https://github.com/BD103/BD103-Python
